setup.py
slbackup.py
slbackup.egg-info/PKG-INFO
slbackup.egg-info/SOURCES.txt
slbackup.egg-info/dependency_links.txt
slbackup.egg-info/not-zip-safe
slbackup.egg-info/requires.txt
slbackup.egg-info/top_level.txt