Metadata-Version: 1.1
Name: slbackup
Version: 2.0
Summary: Backup utility for SWIFT object storage
Home-page: https://github.com/softlayer/softlayer-object-storage-backup
Author: Kevin Landreth
Author-email: klandreth@softlayer.com
License: MIT
Platform: UNKNOWN
Classifier: Development Status :: 5 - Production/Stable
Classifier: Environment :: Console
Classifier: Programming Language :: Python
Classifier: Operating System :: POSIX :: Linux
Classifier: Environment :: Console
Classifier: License :: OSI Approved :: MIT License
